metricllm/__init__.py
metricllm/core/evaluations.py
metricllm/core/metrics.py
metricllm/core/monitor.py
metricllm/core/responsible_ai.py
metricllm/core/traces.py
metricllm/integrations/__init__.py
metricllm/integrations/anthropic_integration.py
metricllm/integrations/bedrock_integration.py
metricllm/integrations/crewai_integration.py
metricllm/integrations/google_integration.py
metricllm/integrations/meta_integration.py
metricllm/integrations/ollama_integration.py
metricllm/integrations/openai_integration.py
metricllm/integrations/xai_integration.py
metricllm/prompts/manager.py
metricllm/storage/config.py
metricllm/storage/database.py
metricllm/storage/file_storage.py
metricllm/storage/file_store.py
metricllm/storage/postgres_storage.py
metricllm/utils/config.py
metricllm/utils/metric_logging.py
metricllm/web/__init__.py
metricllm/web/components.py
metricllm/web/config.yaml.prod
metricllm/web/integrations.py
metricllm-0.1.0b2.dist-info/METADATA
metricllm-0.1.0b2.dist-info/WHEEL
metricllm-0.1.0b2.dist-info/RECORD
