Metadata-Version: 2.3
Name: metricllm
Version: 0.1.0b2
Summary: Add your description here
Requires-Python: >=3.12,<4.0
Classifier: Programming Language :: Python :: 3
Classifier: Programming Language :: Python :: 3.12
Classifier: Programming Language :: Python :: 3.13
Requires-Dist: alembic (>=1.16.1)
Requires-Dist: anthropic (>=0.54.0)
Requires-Dist: bcrypt (>=4.3.0)
Requires-Dist: email-validator (>=2.2.0)
Requires-Dist: fastapi (>=0.115.12)
Requires-Dist: numpy (>=2.3.0)
Requires-Dist: openai (>=1.86.0)
Requires-Dist: pandas (>=2.3.0)
Requires-Dist: passlib (>=1.7.4)
Requires-Dist: plotly (>=6.1.2)
Requires-Dist: psycopg2-binary (>=2.9.10)
Requires-Dist: pydantic (>=2.11.6)
Requires-Dist: pyjwt (>=2.10.1)
Requires-Dist: python-jose (>=3.5.0)
Requires-Dist: python-multipart (>=0.0.20)
Requires-Dist: sqlalchemy (>=2.0.41)
Requires-Dist: streamlit (>=1.45.1)
Requires-Dist: uvicorn (>=0.34.3)
